Workbook

Sheet Dashboard
A1: Life Ledger Dashboard - September 2026 (fictional data)
A3: Total income | B3: =Summary!B1 -> 4800
A4: Total expenses | B4: =Summary!B2 -> 102631.55
A5: Calculated net | B5: =Summary!B3 -> -97831.55
A6: Categories over budget | B6: =COUNTIF(Summary!E9:E15,"OVER BUDGET") -> 3

Sheet Transactions
A1: Date | B1: Description | C1: Category | D1: Type | E1: Amount | F1: Status
A2: 46266 | B2: Paycheque | C2: Income | D2: Income | E2: 2400
A3: 46266 | B3: Rent | C3: Housing | D3: Expense | E3: 1450
A4: 46267 | B4: Grocery run | C4: Groceries | D4: Expense | E4: 86.4
A5: 46268 | B5: PRESTO reload | C5: Transport | D5: Expense | E5: 60
A6: 46269 | B6: Netflix | C6: Subscriptions | D6: Expense | E6: 16.49
A7: 46270 | B7: Lunch with friends | C7: Dining | D7: Expense | E7: 42.75
A8: 46272 | B8: Grocery run | C8: Groceries | D8: Expense | E8: 92.1
A9: 46273 | B9: Python course | C9: Education | D9: Expense | E9: 39.99
A10: 46275 | B10: Ramen night | C10: Dining | D10: Expense | E10: 38
A11: 46277 | B11: Grocery run | C11: Groceries | D11: Expense | E11: 101.25
A12: 46279 | B12: Movie night | C12: Entertainment | D12: Expense | E12: 27.5
A13: 46280 | B13: Paycheque | C13: Income | D13: Income | E13: 2400
... A20: 46290 | B20: Spotify | C20: Subscriptions | D20: Expense | E20: 11.99
A21: 2026-09-31 | B21: Grocery run | C21: Groceries | D21: Expense | E21: 74.2
A22: 46291 | B22: Bookstore | C22: Educaton | D22: Expense | E22: 33
A23: 46292 | B23: Mystery charge | D23: Expense | E23: 19.99
A24: 46292 | B24: Coffee | C24: Dining | D24: Expense | E24: 12.50 CAD
A25: 46293 | B25: Refund | C25: Groceries | D25: Expense | E25: -30
A26: 46293 | B26: Laptop | C26: Education | D26: Expense | E26: 99999
A27: 46392 | B27: Pre-paid gym | C27: Entertainment | D27: Expense | E27: 45
A28: 46294 | B28: Side gig | C28: Income | E28: 120

Sheet Budget
A1: Category | B1: Monthly Limit
A2: Housing | B2: 1500
A3: Groceries | B3: 400
A4: Transport | B4: 180
A5: Dining | B5: 150
A6: Subscriptions | B6: 60
A7: Education | B7: 200
A8: Entertainment | B8: 100

Sheet Rules
A1: Rule | B1: Value
A2: Maximum single transaction | B2: 5000
A3: Reconciliation tolerance | B3: 0.01
A5: Edit only the Value column. The VBA macro reads these cells.

Sheet Summary
A1: Total income | B1: =SUMIFS(Transactions!E:E,Transactions!D:D,"Income") -> 4800
A2: Total expenses | B2: =SUMIFS(Transactions!E:E,Transactions!D:D,"Expense") -> 102631.55
A3: Calculated net | B3: =B1-B2 -> -97831.55
A5: Reported net (typed in from the app) | B5: 2310
A6: B5 is a fictional hardcoded input used to test reconciliation.
A8: Category | B8: Spent | C8: Limit | D8: Remaining | E8: Status
A9: =Budget!A2 -> Housing | B9: =SUMIFS(Transactions!$E:$E,Transactions!$C:$C,A9,Transactions!$D:$D,"Expense") -> 1450 | C9: =Budget!B2 -> 1500 | D9: =C9-B9 -> 50 | E9: =IF(D9<0,"OVER BUDGET","Within budget") -> Within budget
A10: =Budget!A3 -> Groceries | B10: =SUMIFS(Transactions!$E:$E,Transactions!$C:$C,A10,Transactions!$D:$D,"Expense") -> 412.85 | C10: =Budget!B3 -> 400 | D10: =C10-B10 -> -12.85 | E10: =IF(D10<0,"OVER BUDGET","Within budget") -> OVER BUDGET
A11: =Budget!A4 -> Transport | B11: =SUMIFS(Transactions!$E:$E,Transactions!$C:$C,A11,Transactions!$D:$D,"Expense") -> 120 | C11: =Budget!B4 -> 180 | D11: =C11-B11 -> 60 | E11: =IF(D11<0,"OVER BUDGET","Within budget") -> Within budget
A12: =Budget!A5 -> Dining | B12: =SUMIFS(Transactions!$E:$E,Transactions!$C:$C,A12,Transactions!$D:$D,"Expense") -> 148.75 | C12: =Budget!B5 -> 150 | D12: =C12-B12 -> 1.25 | E12: =IF(D12<0,"OVER BUDGET","Within budget") -> Within budget
A13: =Budget!A6 -> Subscriptions | B13: =SUMIFS(Transactions!$E:$E,Transactions!$C:$C,A13,Transactions!$D:$D,"Expense") -> 40.47 | C13: =Budget!B6 -> 60 | D13: =C13-B13 -> 19.53 | E13: =IF(D13<0,"OVER BUDGET","Within budget") -> Within budget
A14: =Budget!A7 -> Education | B14: =SUMIFS(Transactions!$E:$E,Transactions!$C:$C,A14,Transactions!$D:$D,"Expense") -> 100188.99 | C14: =Budget!B7 -> 200 | D14: =C14-B14 -> -99988.99 | E14: =IF(D14<0,"OVER BUDGET","Within budget") -> OVER BUDGET
A15: =Budget!A8 -> Entertainment | B15: =SUMIFS(Transactions!$E:$E,Transactions!$C:$C,A15,Transactions!$D:$D,"Expense") -> 217.5 | C15: =Budget!B8 -> 100 | D15: =C15-B15 -> -117.5 | E15: =IF(D15<0,"OVER BUDGET","Within budget") -> OVER BUDGET

Sheet Accessibility
A1: Check | B1: How this workbook handles it | C1: Verified?
A2: Descriptive sheet names | B2: Sheets are named Dashboard, Transactions, Budget, Rules, Summary, Report, Accessibility. | C2: No
A3: Marked and frozen header rows | B3: Every data sheet has a bold header row; Transactions freezes it. | C3: No
A4: No merged cells or empty rows inside data | B4: Tables are plain grids with no merged cells. | C4: No
A5: Status is not shown by colour alone | B5: Row status and budget status are also written as text (OK / Check / OVER BUDGET). | C5: No
A6: Text and background contrast | B6: Headers use white text on dark navy (1F3864). | C6: No
A7: Charts have titles, axis titles and a text equivalent | B7: Both charts have titles and axis titles; the same figures appear as text on Dashboard and Summary. | C7: No
A8: Plain-language messages | B8: Validation report messages are full sentences that say what to fix. | C8: No
A9: Alt text on both charts | B9: MANUAL: right-click each chart > Edit Alt Text and describe the takeaway. | C9: No
A10: Run Excel's Accessibility Checker | B10: MANUAL: Review > Check Accessibility, then fix every warning. | C10: No
A11: Document title set | B11: MANUAL: File > Info > Properties > Title. | C11: No
